Metadata-Version: 2.1
Name: audioProcessingWisrovi
Version: 0.21.0
Summary: Procesamiento de audios
Home-page: https://github.com/wisrovi/ProcessAudio
Download-URL: http://chardet.feedparser.org/download/python3-chardet-1.0.1.tgz
Author: William Rodriguez
Author-email: wisrovi.rodriguez@gmail.com
License: GPLv3
Keywords: encoding,i18n,xml
Classifier: Programming Language :: Python
Classifier: Programming Language :: Python :: 3
Classifier: License :: OSI Approved :: GNU General Public License v3 (GPLv3)
Classifier: Operating System :: OS Independent
Classifier: Development Status :: 4 - Beta
Classifier: Intended Audience :: Developers
Classifier: Topic :: Software Development :: Libraries :: Python Modules
License-File: LICENSE
License-File: LICENSE.txt
